ka_uts_dfr/__init__.py
ka_uts_dfr/__version__.py
ka_uts_dfr/pddf.py
ka_uts_dfr/pldf.py
ka_uts_dfr/py.typed
ka_uts_dfr-4.1.2.250609.dist-info/licenses/LICENSE.txt
ka_uts_dfr-4.1.2.250609.dist-info/METADATA
ka_uts_dfr-4.1.2.250609.dist-info/WHEEL
ka_uts_dfr-4.1.2.250609.dist-info/top_level.txt
ka_uts_dfr-4.1.2.250609.dist-info/RECORD
